verilog/tsense-SPI.v
//DEFINES
`define RST_COUNT       5'd0
`define CS_LOW_COUNT    5'd4
`define CS_HIGH_COUNT   5'd20
`define WRITE_LSB_COUNT	5'd22
//`define WRITE_LSB_COUNT	5'd24
`define MAX_COUNT       5'd28
`define SPI_IDLE	2'b00
`define SPI_READ	2'b01
`define DISP_WRITE_MSB	2'b10
`define DISP_WRITE_LSB	2'b11

//Verilog code for continous SPI read of LM07
//
module LM07_read(SYSCLK, RSTN, CS, SCK, SIO, disp, dataSeg, dbugout);
  input SYSCLK;		//System clock from the testbench
  input RSTN;		//Active-low reset signal
  input SIO;		//Serial data output from the temp sensor.
  output CS;	//Generate the Chip select for temp sensor
  output reg SCK;	//Generate the SPI clock for temp sensor
  output [1:0] disp;	//7-segment display select lines.
  output [7:0] dataSeg;  //7-segment data
  output [7:0] dbugout;	//the 8-bit data is latched for display
  
  reg SYSCLK_HALF;
  reg [7:0] shift_reg;
  reg [1:0] spi_state;
  reg [4:0] count;
  wire sysclk_gated;
  wire [7:0] temp_bin;
  wire [3:0] bcd_msb;
  wire [3:0] bcd_lsb;
  wire [3:0] bcd_data;

  //This output reg for debug purpose
  //assign dbugout = shift_reg;
  assign dbugout[7:4] = bcd_msb;
  assign dbugout[3:0] = bcd_lsb;
    
  //7-Segment select lines for MSB and LSB
  assign disp[1] = (spi_state == `DISP_WRITE_MSB);
  assign disp[0] = (spi_state == `DISP_WRITE_LSB);

  //2:1 MUX for sending MSB/LSB data to the 7-segment display
  assign bcd_data = (spi_state == `DISP_WRITE_MSB) ? bcd_msb : bcd_lsb ;

  //BCD to 7-segment decoder
  assign dataSeg[7] = (~bcd_data[2] && ~bcd_data[0]) || bcd_data[1] || bcd_data[0] || (bcd_data[2] && bcd_data[0]); //a
  assign dataSeg[6] = ~bcd_data[2] || (~bcd_data[1] && ~bcd_data[0]) || (bcd_data[1] && bcd_data[0]);  //b
  assign dataSeg[5] = ~bcd_data[1] || bcd_data[0] || bcd_data[2]; //c
  assign dataSeg[4] = (~bcd_data[2] && ~bcd_data[0]) || (~bcd_data[2] && bcd_data[1]) || (bcd_data[2] && ~bcd_data[1] && bcd_data[0]) || (bcd_data[1] && ~bcd_data[0]) || bcd_data[3]; //d
  assign dataSeg[3] = (~bcd_data[2] && ~bcd_data[0]) || (bcd_data[1] && ~bcd_data[0]); //e
  assign dataSeg[2] = (~bcd_data[1] && ~bcd_data[0]) || (bcd_data[2] && ~bcd_data[1]) || (bcd_data[2] && ~bcd_data[0]) || bcd_data[3]; //f
  assign dataSeg[1] = (~bcd_data[2] && bcd_data[1]) || (bcd_data[2] && ~bcd_data[1]) || bcd_data[3] || (bcd_data[2] && ~bcd_data[0]); //g
  assign dataSeg[0] = 1'b0; //DP

  //If you are reading 8-bits from the sensor, the LSB is 2-deg C
  //So multiply it by 2 to convert it to the right magnitude.
  assign temp_bin = shift_reg<<1;

  //Converting 7-bit binary to BCD value
  //BCD(MSB) = Temp./10 approx= Temp(1/16 + 1/32)
  //NOTE: First add then shift by 4 to avoid truncation error.
  assign bcd_msb = (temp_bin + (temp_bin>>1))>>4;
  
  //BCD(LSB) = temp - 10*MSB = temp - (8*MSB + 2*MSB)
  assign bcd_lsb = temp_bin - ((bcd_msb<<3) + (bcd_msb<<1));

  //shift register for the input (SIO)
  always @(posedge SCK or negedge RSTN)
    if (~RSTN)
      shift_reg <= 8'h00;
    else
      begin
        shift_reg <= shift_reg<<1;
	shift_reg[0] <= SIO;
      end

  //SPI CLOCK SCK generator
  always @(negedge SYSCLK or negedge RSTN)
    if (~RSTN || CS)
      SCK <= 1'b0;
    else
      SCK <= ~SCK;
  
  // Chip Select CS generator
  assign CS = ~(spi_state == `SPI_READ);

  // 4-state (IDLE, READ, MSB_WRITE, LSB_WRITE) state-machine
  always @(posedge SYSCLK or negedge RSTN)
    if (~RSTN)
      begin	    
        spi_state <= `SPI_IDLE;
      end
    else if ((count >= `CS_LOW_COUNT) && (count < `CS_HIGH_COUNT) )
      begin
        spi_state <= `SPI_READ;
      end
    else if (count == `CS_HIGH_COUNT)
      begin	    
        spi_state <= `DISP_WRITE_MSB;
      end
    else if (count == `WRITE_LSB_COUNT)
      begin	    
        spi_state <= `DISP_WRITE_LSB;
      end
    else 
      begin	    
        spi_state <= `SPI_IDLE;
      end

  //5-bit Counter
  always @(negedge SYSCLK or negedge RSTN)
    if (~RSTN)
       count <= `RST_COUNT;
    else if (count == `MAX_COUNT)
       count <= `RST_COUNT;
    else
       count <= count + 1'b1;

endmodule

verilog/SPI-based TEMPERATURE MONITOR/TB-tsense-SPI.v
// Code your testbench here
// or browse Examples
//
`timescale 1ns/1ps


module tsense_read_tb();
  wire CS, SCK, SIO;
  reg RSTN, SYSCLK;
  wire [7:0] dbugout;
  wire [7:0] dataSeg;
  wire [1:0] disp;


  //Task for simple test
  task testRead;
    begin
        #15   RSTN = 1'b1;
    end
  endtask

  
  //Instiate LM07
  LM07 tsense(.CS(CS), .SCK(SCK), .SIO(SIO));
  //Instiate DUT
  LM07_read dut(.SYSCLK(SYSCLK), .RSTN(RSTN), .CS(CS), .SCK(SCK), .SIO(SIO), .disp(disp), .dataSeg(dataSeg), .dbugout(dbugout) );
  //LM07_read dut(.SYSCLK(SYSCLK), .RSTN(RSTN), .CS(CS), .SCK(SCK), .SIO(SIO), .disp(disp), .dataSeg(dataSeg));
 
  //Initialize CS
  initial RSTN = 1'b0;
  
  //Generate test clock
  initial SYSCLK= 1'b1;
  initial forever #10 SYSCLK = ~SYSCLK;

  //Testbench
  initial
    begin
      //$monitor("time= %0t;data[]=,CS=%b,CLK=%b,SIO=%b,",$time,CS,CLK,SIO);
          
      $dumpfile("dump.vcd");
      $dumpvars(1);
      testRead;
      #1500
      $finish(2);
    end
endmodule

//Define
`define TEMP_SET  16'h0B9F

// Verilog model for the SPI-based temperature 
// sensor LM07 or it's equivalent family.
//
module LM07(CS, SCK, SIO);
  output SIO;
  input SCK, CS;
  //
  // lm07_reg represents the register that stores
  // temperature value after A2D conversion
  // FIXME: Model the A2D
  reg [15:0] shift_reg;
  wire clk_gated;
  
  //Reset at startup
  initial begin
    shift_reg = `TEMP_SET; 
    //shift_reg = shift_reg>>1;
  end
  
  //SIO bit of the LM07 is hardwired output of
  // the MSB of the shift register
  assign SIO = shift_reg[15];
  
  //Gate the clock with CS
  assign clk_gated = ~CS & SCK;
  
  // When CS goes low, load temp_shift_reg with lm07_reg
  // If high, reset
  always @(CS)
   begin
     shift_reg = `TEMP_SET;
     //shift_reg = shift_reg>>1;
   end
  
  //Shift register to shift the loaded temp reg
  //every negedge of the gated clock
  always @(negedge clk_gated)
    begin
      shift_reg = shift_reg<<1;
    end
endmodule

verilog/dump.vcd
$date
	Mon Apr 10 22:03:16 2023
$end
$version
	Icarus Verilog
$end
$timescale
	1ps
$end
$scope module tsense_read_tb $end
$var wire 2 ! disp [1:0] $end
$var wire 8 " dbugout [7:0] $end
$var wire 8 # dataSeg [7:0] $end
$var wire 1 $ SIO $end
$var wire 1 % SCK $end
$var wire 1 & CS $end
$var reg 1 ' RSTN $end
$var reg 1 ( SYSCLK $end
$upscope $end
$enddefinitions $end
$comment Show the parameter values. $end
$dumpall
$end
#0
$dumpvars
1(
0'
1&
0%
0$
b11111100 #
b0 "
b0 !
$end
#10000
0(
#15000
1'
#20000
1(
#30000
0(
#40000
1(
#50000
0(
#60000
1(
#70000
0(
#80000
1(
#90000
0(
#100000
0&
1(
#110000
1%
0(
#120000
1(
#130000
0%
0(
#140000
1(
#150000
1%
0(
#160000
1(
#170000
0%
0(
#180000
1(
#190000
1%
0(
#200000
1(
#210000
0%
0(
#220000
1(
#230000
1%
0(
#240000
1(
#250000
1$
0%
0(
#260000
1(
#270000
b11011010 #
b10 "
1%
0(
#280000
1(
#290000
0$
0%
0(
#300000
1(
#310000
b1100110 #
b100 "
1%
0(
#320000
1(
#330000
1$
0%
0(
#340000
1(
#350000
b11011110 #
b1010 "
1%
0(
#360000
1(
#370000
0%
0(
#380000
1(
#390000
b11011010 #
b100010 "
1%
0(
#400000
1(
#410000
0%
0(
#420000
0$
1&
b10 !
1(
#430000
0(
#440000
b0 !
1(
#450000
0(
#460000
b1 !
1(
#470000
0(
#480000
b0 !
1(
#490000
0(
#500000
1(
#510000
0(
#520000
1(
#530000
0(
#540000
1(
#550000
0(
#560000
1(
#570000
0(
#580000
1(
#590000
0(
#600000
1(
#610000
0(
#620000
1(
#630000
0(
#640000
1(
#650000
0(
#660000
1(
#670000
0(
#680000
0&
1(
#690000
b1100110 #
b1000100 "
1%
0(
#700000
1(
#710000
0%
0(
#720000
1(
#730000
b11111110 #
b10001000 "
1%
0(
#740000
1(
#750000
0%
0(
#760000
1(
#770000
b11111100 #
b0 "
1%
0(
#780000
1(
#790000
0%
0(
#800000
1(
#810000
b10111110 #
b10010110 "
1%
0(
#820000
1(
#830000
1$
0%
0(
#840000
1(
#850000
b10111110 #
b101110 "
1%
0(
#860000
1(
#870000
0$
0%
0(
#880000
1(
#890000
b1110110 #
b11001100 "
1%
0(
#900000
1(
#910000
1$
0%
0(
#920000
1(
#930000
b11011110 #
b1010 "
1%
0(
#940000
1(
#950000
0%
0(
#960000
1(
#970000
b11011010 #
b100010 "
1%
0(
#980000
1(
#990000
0%
0(
#1000000
0$
1&
b10 !
1(
#1010000
0(
#1020000
b0 !
1(
#1030000
0(
#1040000
b1 !
1(
#1050000
0(
#1060000
b0 !
1(
#1070000
0(
#1080000
1(
#1090000
0(
#1100000
1(
#1110000
0(
#1120000
1(
#1130000
0(
#1140000
1(
#1150000
0(
#1160000
1(
#1170000
0(
#1180000
1(
#1190000
0(
#1200000
1(
#1210000
0(
#1220000
1(
#1230000
0(
#1240000
1(
#1250000
0(
#1260000
0&
1(
#1270000
b1100110 #
b1000100 "
1%
0(
#1280000
1(
#1290000
0%
0(
#1300000
1(
#1310000
b11111110 #
b10001000 "
1%
0(
#1320000
1(
#1330000
0%
0(
#1340000
1(
#1350000
b11111100 #
b0 "
1%
0(
#1360000
1(
#1370000
0%
0(
#1380000
1(
#1390000
b10111110 #
b10010110 "
1%
0(
#1400000
1(
#1410000
1$
0%
0(
#1420000
1(
#1430000
b10111110 #
b101110 "
1%
0(
#1440000
1(
#1450000
0$
0%
0(
#1460000
1(
#1470000
b1110110 #
b11001100 "
1%
0(
#1480000
1(
#1490000
1$
0%
0(
#1500000
1(
#1510000
b11011110 #
b1010 "
1%
0(
